bytedance_ba_engines_driver/__init__.py
bytedance_ba_engines_driver-0.0.1.dist-info/METADATA
bytedance_ba_engines_driver-0.0.1.dist-info/WHEEL
bytedance_ba_engines_driver-0.0.1.dist-info/top_level.txt
bytedance_ba_engines_driver-0.0.1.dist-info/RECORD
